{
    "base_experience": 187,
    "pokemon_id": 131,
    "name": "lapras",
    "abilities": [
        93
    ],
    "hp": 130,
    "attack": 85,
    "defense": 80,
    "special-attack": 85,
    "special-defense": 95,
    "speed": 60,
    "types": [
        "water",
        "ice"
    ],
    "moves": [
        {
            "level_learned_at": 0,
            "move_learn_method": "egg",
            "move_id": "32"
        },
        {
            "level_learned_at": 13,
            "move_learn_method": "level-up",
            "move_id": "34"
        },
        {
            "level_learned_at": 0,
            "move_learn_method": "tutor",
            "move_id": "34"
        },
        {
            "level_learned_at": 0,
            "move_learn_method": "tutor",
            "move_id": "38"
        },
        {
            "level_learned_at": 1,
            "move_learn_method": "level-up",
            "move_id": "45"
        },
        {
            "level_learned_at": 0,
            "move_learn_method": "machine",
            "move_id": "46"
        },
        {
            "level_learned_at": 1,
            "move_learn_method": "level-up",
            "move_id": "47"
        },
        {
            "level_learned_at": 7,
            "move_learn_method": "level-up",
            "move_id": "54"
        },
        {
            "level_learned_at": 1,
            "move_learn_method": "level-up",
            "move_id": "55"
        },
        {
            "level_learned_at": 49,
            "move_learn_method": "level-up",
            "move_id": "56"
        },
        {
            "level_learned_at": 0,
            "move_learn_method": "machine",
            "move_id": "57"
        },
        {
            "level_learned_at": 31,
            "move_learn_method": "level-up",
            "move_id": "58"
        },
        {
            "level_learned_at": 0,
            "move_learn_method": "machine",
            "move_id": "58"
        },
        {
            "level_learned_at": 0,
            "move_learn_method": "machine",
            "move_id": "59"
        },
        {
            "level_learned_at": 0,
            "move_learn_method": "machine",
            "move_id": "63"
        },
        {
            "level_learned_at": 0,
            "move_learn_method": "machine",
            "move_id": "70"
        },
        {
            "level_learned_at": 0,
            "move_learn_method": "machine",
            "move_id": "85"
        },
        {
            "level_learned_at": 0,
            "move_learn_method": "machine",
            "move_id": "87"
        },
        {
            "level_learned_at": 0,
            "move_learn_method": "machine",
            "move_id": "92"
        },
        {
            "level_learned_at": 0,
            "move_learn_method": "machine",
            "move_id": "94"
        },
        {
            "level_learned_at": 0,
            "move_learn_method": "tutor",
            "move_id": "102"
        },
        {
            "level_learned_at": 0,
            "move_learn_method": "machine",
            "move_id": "104"
        },
        {
            "level_learned_at": 19,
            "move_learn_method": "level-up",
            "move_id": "109"
        },
        {
            "level_learned_at": 0,
            "move_learn_method": "machine",
            "move_id": "127"
        },
        {
            "level_learned_at": 0,
            "move_learn_method": "tutor",
            "move_id": "138"
        },
        {
            "level_learned_at": 0,
            "move_learn_method": "machine",
            "move_id": "156"
        },
        {
            "level_learned_at": 0,
            "move_learn_method": "egg",
            "move_id": "164"
        },
        {
            "level_learned_at": 0,
            "move_learn_method": "tutor",
            "move_id": "164"
        },
        {
            "level_learned_at": 0,
            "move_learn_method": "egg",
            "move_id": "174"
        },
        {
            "level_learned_at": 0,
            "move_learn_method": "machine",
            "move_id": "182"
        },
        {
            "level_learned_at": 0,
            "move_learn_method": "egg",
            "move_id": "193"
        },
        {
            "level_learned_at": 25,
            "move_learn_method": "level-up",
            "move_id": "195"
        },
        {
            "level_learned_at": 0,
            "move_learn_method": "machine",
            "move_id": "213"
        },
        {
            "level_learned_at": 0,
            "move_learn_method": "egg",
            "move_id": "214"
        },
        {
            "level_learned_at": 0,
            "move_learn_method": "machine",
            "move_id": "216"
        },
        {
            "level_learned_at": 0,
            "move_learn_method": "machine",
            "move_id": "218"
        },
        {
            "level_learned_at": 43,
            "move_learn_method": "level-up",
            "move_id": "219"
        },
        {
            "level_learned_at": 0,
            "move_learn_method": "machine",
            "move_id": "219"
        },
        {
            "level_learned_at": 0,
            "move_learn_method": "machine",
            "move_id": "231"
        },
        {
            "level_learned_at": 0,
            "move_learn_method": "machine",
            "move_id": "237"
        },
        {
            "level_learned_at": 37,
            "move_learn_method": "level-up",
            "move_id": "240"
        },
        {
            "level_learned_at": 0,
            "move_learn_method": "machine",
            "move_id": "240"
        },
        {
            "level_learned_at": 0,
            "move_learn_method": "machine",
            "move_id": "249"
        },
        {
            "level_learned_at": 0,
            "move_learn_method": "machine",
            "move_id": "258"
        },
        {
            "level_learned_at": 0,
            "move_learn_method": "machine",
            "move_id": "263"
        },
        {
            "level_learned_at": 0,
            "move_learn_method": "egg",
            "move_id": "287"
        },
        {
            "level_learned_at": 0,
            "move_learn_method": "machine",
            "move_id": "290"
        },
        {
            "level_learned_at": 0,
            "move_learn_method": "machine",
            "move_id": "291"
        },
        {
            "level_learned_at": 0,
            "move_learn_method": "egg",
            "move_id": "321"
        },
        {
            "level_learned_at": 55,
            "move_learn_method": "level-up",
            "move_id": "329"
        },
        {
            "level_learned_at": 0,
            "move_learn_method": "egg",
            "move_id": "349"
        },
        {
            "level_learned_at": 0,
            "move_learn_method": "machine",
            "move_id": "351"
        },
        {
            "level_learned_at": 0,
            "move_learn_method": "machine",
            "move_id": "352"
        }
    ]
}