[
    {
        "base_experience": 55,
        "pokemon_id": 32,
        "name": "nidoran-m",
        "hp": 46,
        "attack": 57,
        "defense": 40,
        "special-attack": 40,
        "special-defense": 40,
        "speed": 50,
        "types": [
            "poison"
        ],
        "moves": [
            {
                "name": "cut",
                "level_learned_at": 0,
                "move_learn_method": "machine",
                "move_id": "15"
            },
            {
                "name": "double-kick",
                "level_learned_at": 12,
                "move_learn_method": "level-up",
                "move_id": "24"
            },
            {
                "name": "horn-attack",
                "level_learned_at": 20,
                "move_learn_method": "level-up",
                "move_id": "30"
            },
            {
                "name": "fury-attack",
                "level_learned_at": 30,
                "move_learn_method": "level-up",
                "move_id": "31"
            },
            {
                "name": "horn-drill",
                "level_learned_at": 47,
                "move_learn_method": "level-up",
                "move_id": "32"
            },
            {
                "name": "body-slam",
                "level_learned_at": 0,
                "move_learn_method": "tutor",
                "move_id": "34"
            },
            {
                "name": "take-down",
                "level_learned_at": 0,
                "move_learn_method": "egg",
                "move_id": "36"
            },
            {
                "name": "double-edge",
                "level_learned_at": 0,
                "move_learn_method": "tutor",
                "move_id": "38"
            },
            {
                "name": "poison-sting",
                "level_learned_at": 17,
                "move_learn_method": "level-up",
                "move_id": "40"
            },
            {
                "name": "leer",
                "level_learned_at": 1,
                "move_learn_method": "level-up",
                "move_id": "43"
            },
            {
                "name": "supersonic",
                "level_learned_at": 0,
                "move_learn_method": "egg",
                "move_id": "48"
            },
            {
                "name": "disable",
                "level_learned_at": 0,
                "move_learn_method": "egg",
                "move_id": "50"
            },
            {
                "name": "ice-beam",
                "level_learned_at": 0,
                "move_learn_method": "machine",
                "move_id": "58"
            },
            {
                "name": "blizzard",
                "level_learned_at": 0,
                "move_learn_method": "machine",
                "move_id": "59"
            },
            {
                "name": "peck",
                "level_learned_at": 1,
                "move_learn_method": "level-up",
                "move_id": "64"
            },
            {
                "name": "counter",
                "level_learned_at": 0,
                "move_learn_method": "egg",
                "move_id": "68"
            },
            {
                "name": "counter",
                "level_learned_at": 0,
                "move_learn_method": "tutor",
                "move_id": "68"
            },
            {
                "name": "strength",
                "level_learned_at": 0,
                "move_learn_method": "machine",
                "move_id": "70"
            },
            {
                "name": "thunderbolt",
                "level_learned_at": 0,
                "move_learn_method": "machine",
                "move_id": "85"
            },
            {
                "name": "thunder",
                "level_learned_at": 0,
                "move_learn_method": "machine",
                "move_id": "87"
            },
            {
                "name": "dig",
                "level_learned_at": 0,
                "move_learn_method": "machine",
                "move_id": "91"
            },
            {
                "name": "toxic",
                "level_learned_at": 0,
                "move_learn_method": "machine",
                "move_id": "92"
            },
            {
                "name": "confusion",
                "level_learned_at": 0,
                "move_learn_method": "egg",
                "move_id": "93"
            },
            {
                "name": "mimic",
                "level_learned_at": 0,
                "move_learn_method": "tutor",
                "move_id": "102"
            },
            {
                "name": "double-team",
                "level_learned_at": 0,
                "move_learn_method": "machine",
                "move_id": "104"
            },
            {
                "name": "focus-energy",
                "level_learned_at": 8,
                "move_learn_method": "level-up",
                "move_id": "116"
            },
            {
                "name": "amnesia",
                "level_learned_at": 0,
                "move_learn_method": "egg",
                "move_id": "133"
            },
            {
                "name": "rest",
                "level_learned_at": 0,
                "move_learn_method": "machine",
                "move_id": "156"
            },
            {
                "name": "substitute",
                "level_learned_at": 0,
                "move_learn_method": "tutor",
                "move_id": "164"
            },
            {
                "name": "thief",
                "level_learned_at": 0,
                "move_learn_method": "machine",
                "move_id": "168"
            },
            {
                "name": "protect",
                "level_learned_at": 0,
                "move_learn_method": "machine",
                "move_id": "182"
            },
            {
                "name": "sludge-bomb",
                "level_learned_at": 0,
                "move_learn_method": "machine",
                "move_id": "188"
            },
            {
                "name": "attract",
                "level_learned_at": 0,
                "move_learn_method": "machine",
                "move_id": "213"
            },
            {
                "name": "return",
                "level_learned_at": 0,
                "move_learn_method": "machine",
                "move_id": "216"
            },
            {
                "name": "frustration",
                "level_learned_at": 0,
                "move_learn_method": "machine",
                "move_id": "218"
            },
            {
                "name": "iron-tail",
                "level_learned_at": 0,
                "move_learn_method": "machine",
                "move_id": "231"
            },
            {
                "name": "hidden-power",
                "level_learned_at": 0,
                "move_learn_method": "machine",
                "move_id": "237"
            },
            {
                "name": "rain-dance",
                "level_learned_at": 0,
                "move_learn_method": "machine",
                "move_id": "240"
            },
            {
                "name": "sunny-day",
                "level_learned_at": 0,
                "move_learn_method": "machine",
                "move_id": "241"
            },
            {
                "name": "rock-smash",
                "level_learned_at": 0,
                "move_learn_method": "machine",
                "move_id": "249"
            },
            {
                "name": "beat-up",
                "level_learned_at": 0,
                "move_learn_method": "egg",
                "move_id": "251"
            },
            {
                "name": "flatter",
                "level_learned_at": 38,
                "move_learn_method": "level-up",
                "move_id": "260"
            },
            {
                "name": "facade",
                "level_learned_at": 0,
                "move_learn_method": "machine",
                "move_id": "263"
            },
            {
                "name": "helping-hand",
                "level_learned_at": 23,
                "move_learn_method": "level-up",
                "move_id": "270"
            },
            {
                "name": "secret-power",
                "level_learned_at": 0,
                "move_learn_method": "machine",
                "move_id": "290"
            },
            {
                "name": "shock-wave",
                "level_learned_at": 0,
                "move_learn_method": "machine",
                "move_id": "351"
            },
            {
                "name": "water-pulse",
                "level_learned_at": 0,
                "move_learn_method": "machine",
                "move_id": "352"
            }
        ]
    }
]